[
  {
    "key": "9pCiEt",
    "name": "海外看（墙）",
    "api": "https://haiwaikan.com/api.php/provide/vod/",
    "download": "",
    "jiexiUrl": "",
    "group": "影视",
    "isActive": true,
    "reverseOrder": false,
    "status": true,
    "id": 1,
    "type": 1,
    "search": 2
  },
  {
    "key": "4wFLjy",
    "name": "欧乐影院（墙）",
    "api": "https://www.oulevod.tv/api.php/provide/vod/",
    "download": "",
    "jiexiUrl": "",
    "group": "影视",
    "isActive": true,
    "reverseOrder": false,
    "status": true,
    "id": 2,
    "type": 1,
    "search": 2
  },
  {
    "key": "cGkdiY",
    "name": "吼吼（墙）",
    "api": "https://www.hoho.tv/api.php/provide/vod/",
    "download": "",
    "jiexiUrl": "",
    "group": "影视",
    "isActive": true,
    "reverseOrder": false,
    "status": true,
    "id": 3,
    "search": 2,
    "type": 1
  },
  {
    "key": "39kan",
    "name": "39影视",
    "api": "https://www.39kan.com/api.php/provide/vod/",
    "jiexiUrl": "",
    "group": "影视",
    "isActive": true,
    "status": true,
    "type": 1,
    "id": 4,
    "search": 1
  },
  {
    "key": "vipmv",
    "name": "天堂资源",
    "api": "http://vipmv.cc/api.php/provide/vod/",
    "jiexiUrl": "https://titan.mgtv.com.o8tv.com/jiexi/?url=",
    "group": "影视",
    "isActive": true,
    "status": true,
    "type": 1,
    "id": 5,
    "search": 1
  },
  {
    "key": "wolongzyw",
    "name": "卧龙资源(切)",
    "api": "https://collect.wolongzyw.com/api.php/provide/vod/",
    "jiexiUrl": "",
    "group": "影视",
    "isActive": true,
    "status": true,
    "type": 1,
    "id": 6,
    "search": 1
  },
  {
    "key": "lziapi",
    "name": "量子资源(切)",
    "api": "http://cj.lziapi.com/api.php/provide/vod/",
    "jiexiUrl": "",
    "group": "影视",
    "isActive": true,
    "status": true,
    "type": 1,
    "id": 7,
    "search": 1
  },
  {
    "key": "lehootv",
    "name": "乐活影视",
    "api": "https://lehootv.com/api.php/provide/vod/",
    "jiexiUrl": "",
    "group": "影视",
    "isActive": true,
    "status": true,
    "type": 1,
    "id": 9,
    "search": 1
  },
  {
    "key": "apibdzy",
    "name": "百度云资源(切)",
    "api": "https://api.apibdzy.com/api.php/provide/vod/",
    "jiexiUrl": "",
    "group": "影视",
    "isActive": true,
    "status": true,
    "type": 1,
    "id": 11,
    "search": 1
  },
  {
    "key": "wolongzyw",
    "name": "卧龙资源站综合资源",
    "api": "https://collect.wolongzyw.com/api.php/provide/vod/",
    "jiexiUrl": "",
    "group": "影视",
    "isActive": true,
    "status": true,
    "type": 1,
    "id": 13,
    "search": 1
  },
  {
    "key": "taopianapi",
    "name": "淘片资源采集网",
    "api": "https://taopianapi.com/home/cjapi/as/mc10/vod/json",
    "jiexiUrl": "",
    "group": "影视",
    "isActive": true,
    "status": true,
    "type": 1,
    "id": 15,
    "search": 1
  },
  {
    "key": "xinlangapi",
    "name": "新浪资源",
    "api": "https://api.xinlangapi.com/xinlangapi.php/provide/vod/",
    "jiexiUrl": "",
    "group": "影视",
    "isActive": true,
    "status": true,
    "type": 1,
    "id": 16,
    "search": 1
  },
  {
    "key": "yulecj",
    "name": "鱼乐资源网",
    "api": "https://api.yulecj.com/api.php/provide/vod/",
    "jiexiUrl": "",
    "group": "影视",
    "isActive": true,
    "status": true,
    "type": 1,
    "id": 18,
    "search": 1
  },
  {
    "key": "sdzyapi",
    "name": "闪电资源网(切)",
    "api": "https://sdzyapi.com/api.php/provide/vod/",
    "jiexiUrl": "",
    "group": "影视",
    "isActive": true,
    "status": true,
    "type": 1,
    "id": 19,
    "search": 1
  },
  {
    "key": "ckzy",
    "name": "CK资源",
    "api": "https://ckzy.me/api.php/provide/vod/",
    "jiexiUrl": "",
    "group": "影视",
    "isActive": true,
    "status": true,
    "type": 1,
    "id": 21,
    "search": 1
  },
  {
    "key": "jyzyapi",
    "name": "金鹰资源",
    "api": "https://jyzyapi.com/provide/vod/",
    "jiexiUrl": "",
    "group": "影视",
    "isActive": true,
    "status": true,
    "type": 1,
    "id": 23,
    "search": 1
  },
  {
    "key": "tiankongapi",
    "name": "天空资源",
    "api": "https://api.tiankongapi.com/api.php/provide/vod//from/tkm3u8",
    "jiexiUrl": "",
    "group": "影视",
    "isActive": true,
    "status": true,
    "type": 1,
    "id": 24,
    "search": 1
  },
  {
    "key": "feisuzy",
    "name": "飞速资源(切)",
    "api": "https://www.feisuzy.com/api.php/provide/vod/",
    "jiexiUrl": "",
    "group": "影视",
    "isActive": true,
    "status": true,
    "type": 1,
    "id": 25,
    "search": 1
  },
  {
    "key": "ylzy1",
    "name": "鱼乐资源(切)",
    "api": "https://api.ylzy1.com/api.php/provide/vod/",
    "jiexiUrl": "",
    "group": "影视",
    "isActive": true,
    "status": true,
    "id": 26,
    "search": 1,
    "type": 1
  },
  {
    "key": "zzrhgg",
    "name": "飘花资源",
    "api": "http://www.zzrhgg.com/api.php/provide/vod/",
    "jiexiUrl": "",
    "group": "影视",
    "isActive": true,
    "status": true,
    "type": 1,
    "id": 28,
    "search": 1
  },
  {
    "key": "hanjuzy",
    "name": "韩剧资源(切)",
    "api": "http://www.hanjuzy.com/inc/apijson_vod.php",
    "jiexiUrl": "",
    "group": "影视",
    "isActive": true,
    "status": true,
    "type": 1,
    "id": 29,
    "search": 1
  },
  {
    "key": "28393120-9d11-5110-b209-c925b2d8f87e",
    "name": "非凡资源",
    "api": "http://cj.ffzyapi.com/api.php/provide/vod/from/ffm3u8/",
    "download": "",
    "jiexiUrl": "",
    "group": "影视",
    "status": true,
    "isActive": true,
    "type": 1,
    "id": 30,
    "search": 1
  },
  {
    "key": "9fbbb48c-d822-55ed-baee-40964804d8a9",
    "name": "Ikun资源",
    "api": "https://ikunzyapi.com/api.php/provide/vod",
    "download": "",
    "jiexiUrl": "",
    "group": "影视",
    "status": true,
    "isActive": true,
    "type": 1,
    "id": 31,
    "search": 1
  },
  {
    "key": "apiyhzy",
    "name": "樱花动漫",
    "api": "https://m3u8.apiyhzy.com/api.php/provide/vod/",
    "download": "",
    "jiexiUrl": "",
    "group": "影视",
    "status": true,
    "isActive": true,
    "type": 1,
    "id": 32,
    "search": 1
  },
  {
    "key": "U酷资源(优)",
    "name": "U酷资源(优)",
    "api": "https://api.ukuapi.com/api.php/provide/vod/",
    "jiexiUrl": "",
    "group": "优质",
    "isActive": true,
    "status": true,
    "reverseOrder": false,
    "id": 34,
    "type": 1,
    "search": 1
  },
  {
    "key": "天天看(优)",
    "name": "天天看(优)",
    "api": "https://www.ttky8.com/api.php/provide/vod/",
    "jiexiUrl": "",
    "group": "优质",
    "isActive": true,
    "status": true,
    "reverseOrder": false,
    "id": 35,
    "type": 1,
    "search": 1
  },
  {
    "key": "乐活影视(优)",
    "name": "乐活影视(优)",
    "api": "https://lehootv.com/api.php/provide/vod/",
    "jiexiUrl": "",
    "group": "优质",
    "isActive": true,
    "status": true,
    "reverseOrder": false,
    "id": 36,
    "type": 1,
    "search": 1
  },
  {
    "key": "飘花电影(聚)",
    "name": "飘花电影(聚)",
    "api": "http://www.zzrhgg.com/api.php/provide/vod/",
    "jiexiUrl": "",
    "group": "聚合",
    "isActive": true,
    "status": true,
    "reverseOrder": false,
    "id": 37,
    "type": 1,
    "search": 1
  },
  {
    "key": "39影视(聚)",
    "name": "39影视(聚)",
    "api": "https://www.39kan.com/api.php/provide/vod/",
    "jiexiUrl": "",
    "group": "聚合",
    "isActive": true,
    "status": true,
    "reverseOrder": false,
    "id": 38,
    "type": 1,
    "search": 1
  },
  {
    "key": "飘零影院(聚)",
    "name": "飘零影院(聚)",
    "api": "https://p2100.net/api.php/provide/vod/",
    "jiexiUrl": "",
    "group": "聚合",
    "isActive": true,
    "status": true,
    "reverseOrder": false,
    "id": 39,
    "type": 1,
    "search": 1
  },
  {
    "key": "影图(聚)",
    "name": "影图(聚)",
    "api": "https://cj.vodimg.top/api.php/provide/vod/",
    "jiexiUrl": "",
    "group": "聚合",
    "isActive": true,
    "status": true,
    "reverseOrder": false,
    "id": 40,
    "type": 1,
    "search": 1
  },
  {
    "key": "卧龙资源(切)",
    "name": "卧龙资源(切)",
    "api": "https://collect.wolongzyw.com/api.php/provide/vod/",
    "jiexiUrl": "",
    "group": "切片",
    "isActive": true,
    "status": true,
    "reverseOrder": false,
    "id": 41,
    "type": 1,
    "search": 1
  },
  {
    "key": "百度资源(切)",
    "name": "百度资源(切)",
    "api": "https://api.apibdzy.com/api.php/provide/vod/",
    "jiexiUrl": "",
    "group": "切片",
    "isActive": true,
    "status": true,
    "reverseOrder": false,
    "id": 43,
    "type": 1,
    "search": 1
  },
  {
    "key": "鱼乐资源(切)",
    "name": "鱼乐资源(切)",
    "api": "https://api.ylzy1.com/api.php/provide/vod/",
    "jiexiUrl": "",
    "group": "切片",
    "isActive": true,
    "status": true,
    "reverseOrder": false,
    "id": 45,
    "type": 1,
    "search": 1
  },
  {
    "key": "闪电资源(切)",
    "name": "闪电资源(切)",
    "api": "http://sdzyapi.com/api.php/provide/vod/",
    "jiexiUrl": "",
    "group": "切片",
    "isActive": true,
    "status": true,
    "reverseOrder": false,
    "id": 47,
    "type": 1,
    "search": 1
  },
  {
    "key": "量子资源(切)",
    "name": "量子资源(切)",
    "api": "http://cj.lziapi.com/api.php/provide/vod/",
    "jiexiUrl": "",
    "group": "切片",
    "isActive": true,
    "status": true,
    "reverseOrder": false,
    "id": 48,
    "type": 1,
    "search": 1
  },
  {
    "key": "9E6A9BA7661B8B2871F345B7C642C105",
    "name": "乐活影院",
    "api": "https://lehootv.com/api.php/provide/vod/",
    "useInSearchAll": true,
    "isActive": true,
    "group": "常规",
    "reverseOrder": false,
    "status": true,
    "id": 49,
    "type": 1,
    "search": 1
  },
  {
    "key": "DC863C4C546FB4B7743790DFA1993008",
    "name": "百度资源",
    "api": "https://api.apibdzy.com/api.php/provide/vod/",
    "useInSearchAll": true,
    "isActive": true,
    "group": "常规",
    "reverseOrder": false,
    "status": true,
    "id": 51,
    "type": 1,
    "search": 1
  },
  {
    "key": "1399B528FF612B4EFCA3E184C022B2BE",
    "name": "鱼乐资源",
    "api": "https://api.ylzy1.com/api.php/provide/vod/",
    "useInSearchAll": true,
    "isActive": true,
    "group": "常规",
    "reverseOrder": false,
    "status": true,
    "id": 53,
    "type": 1,
    "search": 1
  },
  {
    "key": "41230C9A0AEA6AAFC40304B15EEFC162",
    "name": "量子资源",
    "api": "http://cj.lziapi.com/api.php/provide/vod/",
    "useInSearchAll": true,
    "isActive": true,
    "group": "常规",
    "reverseOrder": false,
    "status": true,
    "id": 55,
    "type": 1,
    "search": 1
  },
  {
    "key": "2529CA9EC6FB50A146984E44C54947A1",
    "name": "U酷资源",
    "api": "https://api.ukuapi.com/api.php/provide/vod/",
    "useInSearchAll": true,
    "isActive": true,
    "group": "常规",
    "reverseOrder": false,
    "status": true,
    "id": 56,
    "type": 1,
    "search": 1
  },
  {
    "key": "D0633291C6A796F8C10441133481E9F9",
    "name": "闪电资源",
    "api": "http://sdzyapi.com/api.php/provide/vod/",
    "useInSearchAll": true,
    "isActive": true,
    "group": "常规",
    "reverseOrder": false,
    "status": true,
    "id": 58,
    "type": 1,
    "search": 1
  },
  {
    "key": "822183CC2F23EBA27777A7588F2B1041",
    "name": "无尽资源1",
    "api": "https://api.wujinapi.com/api.php/provide/vod/",
    "group": "常规",
    "isActive": true,
    "reverseOrder": false,
    "status": true,
    "id": 59,
    "type": 1,
    "search": 1
  },
  {
    "key": "B424455C5FC27549155BF16E59C366D0",
    "name": "天天看",
    "api": "https://www.ttky8.com/api.php/provide/vod/",
    "useInSearchAll": true,
    "isActive": true,
    "group": "常规",
    "reverseOrder": false,
    "status": true,
    "id": 60,
    "type": 1,
    "search": 1
  },
  {
    "key": "DE0EF8F589FED444E4CA11A3FAEFD9F4",
    "name": "追剧达人",
    "api": "http://vipmv.cc/api.php/provide/vod/",
    "useInSearchAll": true,
    "isActive": true,
    "group": "常规",
    "reverseOrder": false,
    "status": true,
    "id": 61,
    "type": 1,
    "search": 1
  },
  {
    "key": "C2850C99DBBAB1270FD997DEE12089A4",
    "name": "卧龙资源",
    "api": "https://www.wolongzyw.com/api.php/provide/vod/",
    "useInSearchAll": true,
    "isActive": true,
    "group": "常规",
    "reverseOrder": false,
    "status": true,
    "id": 62,
    "type": 1,
    "search": 1
  },
  {
    "key": "92AD64EBFE72BDD63F7418071AA5ABB7",
    "name": "飘花电影",
    "api": "http://www.zzrhgg.com/api.php/provide/vod/",
    "useInSearchAll": true,
    "isActive": true,
    "group": "常规",
    "reverseOrder": false,
    "status": true,
    "id": 63,
    "type": 1,
    "search": 1
  },
  {
    "key": "91AAE60CCAE6609C629917A8BBABEDEE",
    "name": "39影院",
    "api": "https://www.39kan.com/api.php/provide/vod/",
    "useInSearchAll": true,
    "isActive": true,
    "group": "常规",
    "reverseOrder": false,
    "status": true,
    "id": 65,
    "type": 1,
    "search": 1
  },
  {
    "key": "82664C03F9D28E67F8A03178A8C854C1",
    "name": "CK资源",
    "api": "http://www.feifei67.com/api.php/provide/vod/",
    "group": "常规",
    "isActive": true,
    "reverseOrder": false,
    "status": true,
    "id": 68,
    "type": 1,
    "search": 1
  },
  {
    "key": "apilyzy",
    "name": "老鸭",
    "api": "https://api.apilyzy.com/api.php/provide/vod/",
    "jiexiUrl": "",
    "group": "18+",
    "isActive": true,
    "status": true,
    "reverseOrder": false,
    "id": 70,
    "type": 1,
    "search": 1
  },
  {
    "key": "apittzy",
    "name": "探探资源",
    "api": "https://apittzy.com/api.php/provide/vod/",
    "jiexiUrl": "",
    "group": "18+",
    "isActive": true,
    "status": true,
    "reverseOrder": false,
    "id": 71,
    "type": 1,
    "search": 1
  },
  {
    "key": "kkzy",
    "name": "KK资源网",
    "api": "https://kkzy.me/api.php/provide/vod/",
    "jiexiUrl": "",
    "group": "18+",
    "isActive": true,
    "status": true,
    "reverseOrder": false,
    "id": 72,
    "type": 1,
    "search": 1
  },
  {
    "key": "shayu",
    "name": "shayu",
    "api": "https://shayuapi.com/api.php/provide/vod/",
    "jiexiUrl": "",
    "group": "18+",
    "isActive": true,
    "status": true,
    "reverseOrder": false,
    "id": 73,
    "type": 1,
    "search": 1
  },
  {
    "key": "lb",
    "name": "乐播",
    "api": "https://lbapi9.com/api.php/provide/vod/",
    "jiexiUrl": "",
    "group": "18+",
    "isActive": true,
    "status": true,
    "reverseOrder": false,
    "id": 74,
    "type": 1,
    "search": 1
  },
  {
    "key": "6087262508D5DA31DDB59B7843E2EE24",
    "name": "鲨鱼资源",
    "api": "https://shayuapi.com/api.php/provide/vod/",
    "useInSearchAll": true,
    "isActive": true,
    "group": "18+",
    "reverseOrder": false,
    "status": true,
    "id": 75,
    "type": 1,
    "search": 1
  },
  {
    "key": "B25D737492A5D48AAE02FEDD0A64E28C",
    "name": "乐播资源",
    "api": "https://lbapi9.com/api.php/provide/vod/",
    "useInSearchAll": true,
    "isActive": true,
    "group": "18+",
    "reverseOrder": false,
    "status": true,
    "id": 77,
    "type": 1,
    "search": 1
  },
  {
    "key": "9840ABFF19CC669F2D4BBF6D35626797",
    "name": "老鸭资源",
    "api": "https://api.apilyzy.com/api.php/provide/vod/",
    "useInSearchAll": true,
    "isActive": true,
    "group": "18+",
    "reverseOrder": false,
    "status": true,
    "id": 78,
    "type": 1,
    "search": 1
  },
  {
    "key": "ECC5170BF22A4C29BB752894DA000CFA",
    "name": "色窝资源",
    "api": "https://sewozyapi.com/api.php/provide/vod/",
    "useInSearchAll": true,
    "isActive": true,
    "group": "18+",
    "reverseOrder": false,
    "status": true,
    "id": 81,
    "type": 1,
    "search": 1
  },
  {
    "key": "C14AD3C2D0BE760499ABB76D2D2E5BF0",
    "name": "芒果资源",
    "api": "https://mgzyz1.com/api.php/provide/vod/",
    "useInSearchAll": true,
    "isActive": true,
    "group": "18+",
    "reverseOrder": false,
    "status": true,
    "id": 84,
    "type": 1,
    "search": 1
  },
  {
    "key": "C7rerH",
    "name": "KK写真",
    "api": "https://kkzy.me/api.php/provide/vod/",
    "download": "",
    "jiexiUrl": "",
    "group": "18+",
    "isActive": true,
    "reverseOrder": false,
    "status": true,
    "id": 86,
    "type": 1,
    "search": 1
  },
  {
    "key": "A5830495BA804C7451C2CF1CA23CB2DA",
    "name": "探探资源",
    "api": "https://apittzy.com/api.php/provide/vod/",
    "useInSearchAll": true,
    "isActive": true,
    "group": "18+",
    "reverseOrder": false,
    "status": true,
    "id": 87,
    "type": 1,
    "search": 1
  },
  {
    "key": "2Luala",
    "name": "辣椒资源",
    "api": "https://apilj.com/api.php/provide/vod/",
    "download": "",
    "jiexiUrl": "",
    "group": "18+",
    "isActive": true,
    "reverseOrder": false,
    "status": true,
    "id": 89,
    "type": 1,
    "search": 1
  }
]